glm_express/__init__.py
glm_express/aggregator/__init__.py
glm_express/aggregator/aggregator.py
glm_express/build_info/__init__.py
glm_express/build_info/build_task_info.py
glm_express/group_level/__init__.py
glm_express/group_level/group.py
glm_express/rest/__init__.py
glm_express/rest/build.py
glm_express/rest/dev.py
glm_express/rest/resting_state.py
glm_express/subject/__init__.py
glm_express/subject/bids_pointer.py
glm_express/subject/subject.py
glm_express-2.0.3.dist-info/LICENSE
glm_express-2.0.3.dist-info/METADATA
glm_express-2.0.3.dist-info/WHEEL
glm_express-2.0.3.dist-info/top_level.txt
glm_express-2.0.3.dist-info/RECORD
