Metadata-Version: 2.1
Name: glm-express
Version: 2.0.3
Summary: Automated linear models for functional neuroimaging data
Home-page: https://github.com/IanRFerguson/glm-express
Author: Ian Richard Ferguson
Author-email: IRF229@nyu.edu
License: MIT
Classifier: License :: OSI Approved :: MIT License
Classifier: Programming Language :: Python :: 3
Classifier: Programming Language :: Python :: 3.7
License-File: LICENSE
Requires-Dist: nilearn
Requires-Dist: pandas
Requires-Dist: tqdm
Requires-Dist: matplotlib
Requires-Dist: numpy
Requires-Dist: pybids
Requires-Dist: nibabel
Requires-Dist: nltools
